Password_Generator/__init__.py
Password_Generator/generate_senp.py
Generator_pass_1.0.1-1.0.1.dist-info/METADATA
Generator_pass_1.0.1-1.0.1.dist-info/WHEEL
Generator_pass_1.0.1-1.0.1.dist-info/top_level.txt
Generator_pass_1.0.1-1.0.1.dist-info/RECORD
