Metadata-Version: 2.1
Name: Generator-pass-1.0.1
Version: 1.0.1
Summary: Un générateur de mots de passe simple
Home-page: https://github.com/livens-coder/PasswordGenerator-v1.0.1
Author: Nicolas Livenson, Jean Duckens SANNON
Author-email: nicolaslivenson@gmail.com, jeanduckens.sanon@esih.edu
License: MIT
Project-URL: GitHub, https://github.com/livens-coder/PasswordGenerator-v1.0.1
Keywords: password generator security
Classifier: Development Status :: 3 - Alpha
Classifier: Intended Audience :: Developers
Classifier: License :: OSI Approved :: MIT License
Classifier: Programming Language :: Python :: 3.6
Classifier: Programming Language :: Python :: 3.7
Classifier: Programming Language :: Python :: 3.8
Classifier: Programming Language :: Python :: Implementation :: CPython
Classifier: Programming Language :: Python :: Implementation :: PyPy
